{
    "matches": [
        {
            "time": "19:00",
            "country": "England",
            "league": "EFL Trophy",
            "competition": "England - EFL Trophy",
            "match": "Peterborough United vs Cheltenham Town",
            "links": [
                "https://thedaddy.to/embed/stream-36.php"
            ]
        },
        {
            "time": "19:45",
            "country": "England",
            "league": "Championship",
            "competition": "England - Championship",
            "match": "Coventry City vs Leeds United",
            "links": [
                "https://thedaddy.to/embed/stream-77.php"
            ]
        },
        {
            "time": "20:00",
            "country": "Spain",
            "league": "Copa del Rey",
            "competition": "Spain - Copa del Rey",
            "match": "Legan\u00e9s vs Real Madrid",
            "links": [
                "https://thedaddy.to/embed/stream-9.php",
                "https://thedaddy.to/embed/stream-571.php",
                "https://thedaddy.to/embed/stream-49.php"
            ]
        },
        {
            "time": "20:00",
            "country": "England",
            "league": "League Cup",
            "competition": "England - League Cup",
            "match": "Newcastle United vs Arsenal",
            "links": [
                "https://thedaddy.to/embed/stream-35.php",
                "https://thedaddy.to/embed/stream-38.php",
                "https://thedaddy.to/embed/stream-74.php"
            ]
        }
    ]
}