{
    "matches": [
        {
            "time": "13:00",
            "country": "World Cup Qualifying",
            "league": null,
            "competition": "World Cup Qualifying",
            "match": "Korea DPR vs Uzbekistan",
            "links": [
                "https://thedaddy.to/embed/stream-465.php",
                "https://thedaddy.to/embed/stream-103.php",
                "https://thedaddy.to/embed/stream-95.php"
            ]
        },
        {
            "time": "13:00",
            "country": "World Cup Qualifying",
            "league": null,
            "competition": "World Cup Qualifying",
            "match": "Indonesia vs Saudi Arabia",
            "links": [
                "https://thedaddy.to/embed/stream-379.php",
                "https://thedaddy.to/embed/stream-468.php",
                "https://thedaddy.to/embed/stream-102.php"
            ]
        },
        {
            "time": "13:00",
            "country": "World Cup Qualifying",
            "league": null,
            "competition": "World Cup Qualifying",
            "match": "China vs Japan",
            "links": [
                "https://thedaddy.to/embed/stream-571.php",
                "https://thedaddy.to/embed/stream-1.php",
                "https://thedaddy.to/embed/stream-925.php"
            ]
        },
        {
            "time": "14:00",
            "country": "Africa Cup of Nations Qualification",
            "league": null,
            "competition": "Africa Cup of Nations Qualification",
            "match": "Kenya vs Namibia",
            "links": [
                "https://thedaddy.to/embed/stream-419.php"
            ]
        },
        {
            "time": "14:00",
            "country": "Africa Cup of Nations Qualification",
            "league": null,
            "competition": "Africa Cup of Nations Qualification",
            "match": "Cameroon vs Zimbabwe",
            "links": [
                "https://thedaddy.to/embed/stream-49.php",
                "https://thedaddy.to/embed/stream-116.php",
                "https://thedaddy.to/embed/stream-486.php"
            ]
        },
        {
            "time": "15:00",
            "country": "World Cup Qualifying",
            "league": null,
            "competition": "World Cup Qualifying",
            "match": "Kyrgyzstan vs Iran",
            "links": [
                "https://thedaddy.to/embed/stream-2.php",
                "https://thedaddy.to/embed/stream-468.php",
                "https://thedaddy.to/embed/stream-453.php"
            ]
        },
        {
            "time": "15:00",
            "country": "World Cup Qualifying",
            "league": null,
            "competition": "World Cup Qualifying",
            "match": "Palestine vs Korea Republic",
            "links": [
                "https://thedaddy.to/embed/stream-3.php",
                "https://thedaddy.to/embed/stream-571.php",
                "https://thedaddy.to/embed/stream-925.php"
            ]
        },
        {
            "time": "16:00",
            "country": "Africa Cup of Nations Qualification",
            "league": null,
            "competition": "Africa Cup of Nations Qualification",
            "match": "Mauritania vs Cape Verde Islands",
            "links": [
                "https://thedaddy.to/embed/stream-290.php",
                "https://thedaddy.to/embed/stream-95.php"
            ]
        },
        {
            "time": "16:00",
            "country": "Africa Cup of Nations Qualification",
            "league": null,
            "competition": "Africa Cup of Nations Qualification",
            "match": "Egypt vs Botswana",
            "links": [
                "https://thedaddy.to/embed/stream-425.php",
                "https://thedaddy.to/embed/stream-372.php",
                "https://thedaddy.to/embed/stream-495.php"
            ]
        },
        {
            "time": "17:00",
            "country": "World Cup Qualifying",
            "league": null,
            "competition": "World Cup Qualifying",
            "match": "Oman vs Iraq",
            "links": [
                "https://thedaddy.to/embed/stream-468.php",
                "https://thedaddy.to/embed/stream-103.php",
                "https://thedaddy.to/embed/stream-92.php"
            ]
        },
        {
            "time": "17:00",
            "country": "World Cup Qualifying",
            "league": null,
            "competition": "World Cup Qualifying",
            "match": "United Arab Emirates vs Qatar",
            "links": [
                "https://thedaddy.to/embed/stream-571.php",
                "https://thedaddy.to/embed/stream-467.php",
                "https://thedaddy.to/embed/stream-102.php"
            ]
        },
        {
            "time": "17:00",
            "country": "Africa Cup of Nations Qualification",
            "league": null,
            "competition": "Africa Cup of Nations Qualification",
            "match": "Sierra Leone vs Zambia",
            "links": [
                "https://thedaddy.to/embed/stream-56.php",
                "https://thedaddy.to/embed/stream-144.php"
            ]
        },
        {
            "time": "17:00",
            "country": "Africa Cup of Nations Qualification",
            "league": null,
            "competition": "Africa Cup of Nations Qualification",
            "match": "C\u00f4te d\u2019Ivoire vs Chad",
            "links": [
                "https://thedaddy.to/embed/stream-117.php",
                "https://thedaddy.to/embed/stream-487.php"
            ]
        },
        {
            "time": "17:00",
            "country": "Africa Cup of Nations Qualification",
            "league": null,
            "competition": "Africa Cup of Nations Qualification",
            "match": "Tanzania vs Guinea",
            "links": [
                "https://thedaddy.to/embed/stream-486.php",
                "https://thedaddy.to/embed/stream-418.php"
            ]
        },
        {
            "time": "17:00",
            "country": "Africa Cup of Nations Qualification",
            "league": null,
            "competition": "Africa Cup of Nations Qualification",
            "match": "Congo DR vs Ethiopia",
            "links": [
                "https://thedaddy.to/embed/stream-415.php"
            ]
        },
        {
            "time": "17:00",
            "country": "Africa Cup of Nations Qualification",
            "league": null,
            "competition": "Africa Cup of Nations Qualification",
            "match": "Guinea-Bissau vs Mozambique",
            "links": [
                "https://thedaddy.to/embed/stream-49.php",
                "https://thedaddy.to/embed/stream-417.php"
            ]
        },
        {
            "time": "17:00",
            "country": "Africa Cup of Nations Qualification",
            "league": null,
            "competition": "Africa Cup of Nations Qualification",
            "match": "Mali vs Eswatini",
            "links": [
                "https://thedaddy.to/embed/stream-496.php",
                "https://thedaddy.to/embed/stream-488.php"
            ]
        },
        {
            "time": "17:00",
            "country": "Africa Cup of Nations Qualification",
            "league": null,
            "competition": "Africa Cup of Nations Qualification",
            "match": "Congo vs Uganda",
            "links": [
                "https://thedaddy.to/embed/stream-420.php"
            ]
        },
        {
            "time": "17:00",
            "country": "Africa Cup of Nations Qualification",
            "league": null,
            "competition": "Africa Cup of Nations Qualification",
            "match": "South Africa vs South Sudan",
            "links": [
                "https://thedaddy.to/embed/stream-1.php",
                "https://thedaddy.to/embed/stream-419.php",
                "https://thedaddy.to/embed/stream-413.php"
            ]
        },
        {
            "time": "19:15",
            "country": "World Cup Qualifying",
            "league": null,
            "competition": "World Cup Qualifying",
            "match": "Bahrain vs Australia",
            "links": [
                "https://thedaddy.to/embed/stream-571.php",
                "https://thedaddy.to/embed/stream-386.php",
                "https://thedaddy.to/embed/stream-2.php"
            ]
        },
        {
            "time": "19:15",
            "country": "World Cup Qualifying",
            "league": null,
            "competition": "World Cup Qualifying",
            "match": "Kuwait vs Jordan",
            "links": [
                "https://thedaddy.to/embed/stream-103.php",
                "https://thedaddy.to/embed/stream-91.php"
            ]
        },
        {
            "time": "20:00",
            "country": "Africa Cup of Nations Qualification",
            "league": null,
            "competition": "Africa Cup of Nations Qualification",
            "match": "Senegal vs Burundi",
            "links": [
                "https://thedaddy.to/embed/stream-117.php",
                "https://thedaddy.to/embed/stream-486.php"
            ]
        },
        {
            "time": "20:45",
            "country": "UEFA Nations League",
            "league": null,
            "competition": "UEFA Nations League",
            "match": "Simulcast",
            "links": [
                "https://thedaddy.to/embed/stream-638.php",
                "https://thedaddy.to/embed/stream-645.php"
            ]
        },
        {
            "time": "20:45",
            "country": "UEFA Nations League",
            "league": null,
            "competition": "UEFA Nations League",
            "match": "Albania vs Ukraine",
            "links": [
                "https://thedaddy.to/embed/stream-756.php",
                "https://thedaddy.to/embed/stream-593.php",
                "https://thedaddy.to/embed/stream-3.php"
            ]
        },
        {
            "time": "20:45",
            "country": "UEFA Nations League",
            "league": null,
            "competition": "UEFA Nations League",
            "match": "Czech Republic vs Georgia",
            "links": [
                "https://thedaddy.to/embed/stream-589.php",
                "https://thedaddy.to/embed/stream-4.php",
                "https://thedaddy.to/embed/stream-7.php"
            ]
        },
        {
            "time": "20:45",
            "country": "UEFA Nations League",
            "league": null,
            "competition": "UEFA Nations League",
            "match": "Montenegro vs Turkey",
            "links": [
                "https://thedaddy.to/embed/stream-8.php",
                "https://thedaddy.to/embed/stream-9.php",
                "https://thedaddy.to/embed/stream-426.php"
            ]
        },
        {
            "time": "20:45",
            "country": "UEFA Nations League",
            "league": null,
            "competition": "UEFA Nations League",
            "match": "Wales vs Iceland",
            "links": [
                "https://thedaddy.to/embed/stream-670.php",
                "https://thedaddy.to/embed/stream-10.php",
                "https://thedaddy.to/embed/stream-590.php"
            ]
        },
        {
            "time": "20:45",
            "country": "UEFA Nations League",
            "league": null,
            "competition": "UEFA Nations League",
            "match": "Bosnia and Herzegovina vs Netherlands",
            "links": [
                "https://thedaddy.to/embed/stream-758.php",
                "https://thedaddy.to/embed/stream-12.php",
                "https://thedaddy.to/embed/stream-13.php"
            ]
        },
        {
            "time": "20:45",
            "country": "UEFA Nations League",
            "league": null,
            "competition": "UEFA Nations League",
            "match": "Hungary vs Germany",
            "links": [
                "https://thedaddy.to/embed/stream-15.php",
                "https://thedaddy.to/embed/stream-727.php",
                "https://thedaddy.to/embed/stream-588.php"
            ]
        },
        {
            "time": "20:45",
            "country": "UEFA Nations League",
            "league": null,
            "competition": "UEFA Nations League",
            "match": "Slovakia vs Estonia",
            "links": [
                "https://thedaddy.to/embed/stream-596.php",
                "https://thedaddy.to/embed/stream-17.php",
                "https://thedaddy.to/embed/stream-18.php"
            ]
        },
        {
            "time": "20:45",
            "country": "UEFA Nations League",
            "league": null,
            "competition": "UEFA Nations League",
            "match": "Sweden vs Azerbaijan",
            "links": [
                "https://thedaddy.to/embed/stream-19.php",
                "https://thedaddy.to/embed/stream-20.php",
                "https://thedaddy.to/embed/stream-592.php"
            ]
        },
        {
            "time": "20:45",
            "country": "UEFA Nations League",
            "league": null,
            "competition": "UEFA Nations League",
            "match": "Malta vs Andorra",
            "links": [
                "https://thedaddy.to/embed/stream-594.php"
            ]
        },
        {
            "time": "21:00",
            "country": "World Cup Qualifying",
            "league": null,
            "competition": "World Cup Qualifying",
            "match": "Bolivia vs Paraguay",
            "links": [
                "https://thedaddy.to/embed/stream-746.php",
                "https://thedaddy.to/embed/stream-80.php"
            ]
        },
        {
            "time": "00:00",
            "country": "World Cup Qualifying",
            "league": null,
            "competition": "World Cup Qualifying",
            "match": "Colombia vs Ecuador",
            "links": [
                "https://thedaddy.to/embed/stream-1.php",
                "https://thedaddy.to/embed/stream-4.php",
                "https://thedaddy.to/embed/stream-71.php"
            ]
        },
        {
            "time": "01:00",
            "country": "World Cup Qualifying",
            "league": null,
            "competition": "World Cup Qualifying",
            "match": "Argentina vs Peru",
            "links": [
                "https://thedaddy.to/embed/stream-746.php",
                "https://thedaddy.to/embed/stream-451.php",
                "https://thedaddy.to/embed/stream-521.php"
            ]
        },
        {
            "time": "01:00",
            "country": "World Cup Qualifying",
            "league": null,
            "competition": "World Cup Qualifying",
            "match": "Chile vs Venezuela",
            "links": [
                "https://thedaddy.to/embed/stream-5.php",
                "https://thedaddy.to/embed/stream-72.php",
                "https://thedaddy.to/embed/stream-138.php"
            ]
        },
        {
            "time": "01:30",
            "country": "CONCACAF Nations League",
            "league": null,
            "competition": "CONCACAF Nations League",
            "match": "Canada vs Suriname",
            "links": [
                "https://thedaddy.to/embed/stream-379.php",
                "https://thedaddy.to/embed/stream-102.php"
            ]
        },
        {
            "time": "01:45",
            "country": "World Cup Qualifying",
            "league": null,
            "competition": "World Cup Qualifying",
            "match": "Brazil vs Uruguay",
            "links": [
                "https://thedaddy.to/embed/stream-78.php",
                "https://thedaddy.to/embed/stream-845.php",
                "https://thedaddy.to/embed/stream-2.php"
            ]
        },
        {
            "time": "03:30",
            "country": "CONCACAF Nations League",
            "league": null,
            "competition": "CONCACAF Nations League",
            "match": "Mexico vs Honduras",
            "links": [
                "https://thedaddy.to/embed/stream-844.php",
                "https://thedaddy.to/embed/stream-66.php",
                "https://thedaddy.to/embed/stream-132.php"
            ]
        }
    ]
}